ExoEcho/Analysis.ipynb
ExoEcho/Ariel.py
ExoEcho/Ariel_Target_Comparison_List.csv
ExoEcho/Ariel_Target_List.csv
ExoEcho/Billy_Edwards_Comparison.ipynb
ExoEcho/EfficiencyTesting.ipynb
ExoEcho/Functions.py
ExoEcho/PlotPrecisionPlots.ipynb
ExoEcho/Telescope.py
ExoEcho/__init__.py
ExoEcho/addTelescopes.ipynb
ExoEcho/plotSNRProfiles.ipynb
ExoEcho/plotTieredProfiles.ipynb
ExoEcho/test_exoecho.ipynb
ExoEcho/Ariel Observations/Ariel_MCS_Known_2024-03-27_ObservationTable.parquet
ExoEcho/Ariel Observations/Ariel_MCS_TPCs_2024-03-27_ObservationTable.parquet
ExoEcho/Billy Edwards Comparisons/Cumulative_Time_vs_Targets.png
ExoEcho/Billy Edwards Comparisons/ESM_TSM_Observations_SNR.png
ExoEcho/Billy Edwards Comparisons/ESM_TSM_Observations_diff.png
ExoEcho/Billy Edwards Comparisons/ESM_TSM_SNR.png
ExoEcho/Billy Edwards Comparisons/ExoEcho_Edwards_Observation_Diff.png
ExoEcho/Results Plots/Cumulative_Time_vs_Targets Tier 1.png
ExoEcho/Results Plots/Cumulative_Time_vs_Targets all Tiers.png
ExoEcho/Results Plots/Cumulative_Time_vs_Targets.png
ExoEcho/Results Plots/Number of Phase Curve Obsevations for Each Target.png
ExoEcho/Results Plots/num_obs_snr.png
ExoEcho/Results Plots/num_obs_snr_LimitedMethods_Tier1.png
ExoEcho/Results Plots/num_obs_snr_LimitedMethods_Tier2.png
ExoEcho/Results Plots/num_obs_snr_LimitedMethods_Tier3.png
ExoEcho/Results Plots/num_obs_snr_lowestObservations.png
ExoEcho/TelescopeNoiseEstimates.egg-info/PKG-INFO
ExoEcho/TelescopeNoiseEstimates.egg-info/SOURCES.txt
ExoEcho/TelescopeNoiseEstimates.egg-info/dependency_links.txt
ExoEcho/TelescopeNoiseEstimates.egg-info/requires.txt
ExoEcho/TelescopeNoiseEstimates.egg-info/top_level.txt
ExoEcho/Telescopes/Ariel/Ariel_MCS_Known_2024-03-27/Ariel AIRS CH0 1.95-3.9um D=1 R=100 tau=0.18/ESM.parquet
ExoEcho/Telescopes/Ariel/Ariel_MCS_Known_2024-03-27/Ariel AIRS CH0 1.95-3.9um D=1 R=100 tau=0.18/Eclipse Flux.parquet
ExoEcho/Telescopes/Ariel/Ariel_MCS_Known_2024-03-27/Ariel AIRS CH0 1.95-3.9um D=1 R=100 tau=0.18/Full Phase Curve Noise.parquet
ExoEcho/Telescopes/Ariel/Ariel_MCS_Known_2024-03-27/Ariel AIRS CH0 1.95-3.9um D=1 R=100 tau=0.18/Full Phase Curve SNR.parquet
ExoEcho/Telescopes/Ariel/Ariel_MCS_Known_2024-03-27/Ariel AIRS CH0 1.95-3.9um D=1 R=100 tau=0.18/Noise.parquet
ExoEcho-0.1.6.dist-info/LICENSE
ExoEcho-0.1.6.dist-info/METADATA
ExoEcho-0.1.6.dist-info/WHEEL
ExoEcho-0.1.6.dist-info/top_level.txt
ExoEcho-0.1.6.dist-info/RECORD
