Metadata-Version: 2.1
Name: ExoEcho
Version: 0.1.6
Summary: To estimate the noise of various telescopes conducting exoplanet-related observations.
Author-email: Ben Coull-Neveu <benjamin.coull-neveu@mail.mcgill.ca>
License: Copyright (c) 2024, Ben Coull-Neveu
Keywords: Ariel,JWST,Noise,Telescope Noise,Noise Estimate
Classifier: Intended Audience :: Science/Research
Classifier: License :: OSI Approved :: BSD License
Classifier: Operating System :: OS Independent
Classifier: Programming Language :: Python :: 3
Classifier: Topic :: Scientific/Engineering :: Astronomy
Requires-Python: >=3.11
License-File: LICENSE
Requires-Dist: pandas >=1.1
Requires-Dist: numpy >=1.19
Requires-Dist: matplotlib >=3.3
Requires-Dist: astropy >=4.2
Requires-Dist: scipy >=1.5
Requires-Dist: modin >=0.31.0
Requires-Dist: pyarrow >=16.1.0
Requires-Dist: numba >=0.59.0
